async_executor.py
async_executor-0.1.2.dist-info/LICENSE
async_executor-0.1.2.dist-info/METADATA
async_executor-0.1.2.dist-info/WHEEL
async_executor-0.1.2.dist-info/top_level.txt
async_executor-0.1.2.dist-info/RECORD
