Metadata-Version: 2.1
Name: async-executor
Version: 0.1.2
Summary: Async execution pool
Home-page: https://github.com/nvllsvm/python-async-executor
Author: Andrew Rabert
Author-email: ar@nullsum.net
License-File: LICENSE
